visonic/__init__.py
visonic/alarm.py
visonicalarm2-3.3.6.dist-info/licenses/LICENSE
visonicalarm2-3.3.6.dist-info/METADATA
visonicalarm2-3.3.6.dist-info/WHEEL
visonicalarm2-3.3.6.dist-info/top_level.txt
visonicalarm2-3.3.6.dist-info/RECORD
