Metadata-Version: 2.4
Name: visonicalarm2
Version: 3.3.6
Summary: A simple API library for the Visonic/Bentel/Tyco Alarm system.
Home-page: https://github.com/And3rsL/VisonicAlarm2
Author: Andrea Liosi
Author-email: andrea.liosi@gmail.com
Classifier: Programming Language :: Python :: 3
Classifier: License :: OSI Approved :: MIT License
Classifier: Operating System :: OS Independent
License-File: LICENSE
Requires-Dist: requests>=2.25.0
Requires-Dist: python-dateutil>=2.8.0
Dynamic: author
Dynamic: author-email
Dynamic: classifier
Dynamic: home-page
Dynamic: license-file
Dynamic: requires-dist
Dynamic: summary
